README.md
setup.py
prohosting24/__init__.py
prohosting24api.egg-info/PKG-INFO
prohosting24api.egg-info/SOURCES.txt
prohosting24api.egg-info/dependency_links.txt
prohosting24api.egg-info/requires.txt
prohosting24api.egg-info/top_level.txt