Metadata-Version: 2.1
Name: prohosting24api
Version: 0.2
Summary: Communicate with the ProHosting24 internal api.
Home-page: https://github.com/AdriBloober/Python_ProHosting24API
Author: AdriBloober
Author-email: adrianbloober@gmail.com
License: UNKNOWN
Platform: UNKNOWN
Classifier: Programming Language :: Python :: 3
Classifier: License :: OSI Approved :: MIT License
Classifier: Operating System :: OS Independent
Requires-Python: >=3.6
